flattrclient/activities.py
flattrclient/categories.py
flattrclient/config.py
flattrclient/languages.py
flattrclient/exc.py
flattrclient/validators.py
flattrclient/base.py
flattrclient/flattrs.py
flattrclient/__init__.py
flattrclient/oauth.py
flattrclient/resource.py
flattrclient/search.py
flattrclient/subscriptions.py
flattrclient/things.py
flattrclient/user.py
flattrclient/api.py
flattrclient/tests/http_server.py
flattrclient/tests/test_api.py
flattrclient/tests/test_decorators.py
flattrclient/tests/test_exc.py
flattrclient/tests/test_flattrs.py
flattrclient/tests/test_resource.py
flattrclient/tests/test_search.py
flattrclient/tests/test_subscriptions.py
flattrclient/tests/test_thing.py
flattrclient/tests/test_user.py
flattrclient/tests/test_validators.py
flattrclient-0.2.dist-info/entry_points.txt
flattrclient-0.2.dist-info/top_level.txt
flattrclient-0.2.dist-info/METADATA
flattrclient-0.2.dist-info/DESCRIPTION.rst
flattrclient-0.2.dist-info/metadata.json
flattrclient-0.2.dist-info/WHEEL
flattrclient-0.2.dist-info/RECORD
