Metadata-Version: 2.0
Name: flattrclient
Version: 0.2
Summary: Implementation of a python library for the flattr restful api
Home-page: https://github.com/chrigl/python-flattr
Author: Christoph Glaubitz
Author-email: chris@chrigl.de
License: Apache License 2.0
Keywords: flattr
Platform: UNKNOWN
Classifier: Development Status :: 4 - Beta
Classifier: License :: OSI Approved :: Apache Software License
Classifier: Intended Audience :: Developers
Classifier: Topic :: Software Development :: Libraries
Classifier: Programming Language :: Python
Classifier: Programming Language :: Python :: 2.7
Classifier: Programming Language :: Python :: 3.4
Requires-Dist: six
Requires-Dist: requests
Requires-Dist: simplejson
